<?xml version="1.0" encoding="utf-8" ?>
<dwsync>
<file name="analytics.js" server="hekuan.me//var/www/html/" local="131094371910000000" remote="131094371910000000" Dst="0" />
<file name="three.min.js" server="hekuan.me//var/www/html/" local="130711643000000000" remote="130711643000000000" Dst="0" />
<file name="math.min.js" server="hekuan.me//var/www/html/" local="130609639060000000" remote="130609639060000000" Dst="0" />
<file name="jquery-1.11.2.min.js" server="hekuan.me//var/www/html/" local="130712164840000000" remote="130712164840000000" Dst="0" />
<file name="sylvester.src.js" server="hekuan.me//var/www/html/" local="130611053500000000" remote="130611053500000000" Dst="0" />
<file name="GeometryUtils.js" server="hekuan.me//var/www/html/" local="130608984620000000" remote="130608984620000000" Dst="0" />
<file name="processing.min.js" server="hekuan.me//var/www/html/" local="130715216940000000" remote="130715216940000000" Dst="0" />
<file name="createText_func.js" server="hekuan.me//var/www/html/" local="130720790000000000" remote="130720790000000000" Dst="0" />
<file name="stats.min.js" server="hekuan.me//var/www/html/" local="130711643100000000" remote="130711643100000000" Dst="0" />
<file name="katex.min.js" server="hekuan.me//var/www/html/" local="130712342620000000" remote="130712342620000000" Dst="0" />
<file name="MathJax.js" server="hekuan.me//var/www/html/" local="130485774900000000" remote="130485774900000000" Dst="0" />
<file name="jquery-1.11.1.min.js" server="hekuan.me//var/www/html/" local="130609006020000000" remote="130609006020000000" Dst="0" />
<file name="newOrbit.js" server="hekuan.me//var/www/html/" local="130611411480000000" remote="130611411480000000" Dst="0" />
<file name="Projector.js" server="hekuan.me//var/www/html/" local="130711536080000000" remote="130711536080000000" Dst="0" />
<file name="OrbitControls.js" server="hekuan.me//var/www/html/" local="130631848000000000" remote="130631848000000000" Dst="0" />
<file name="TrackballControls.js" server="hekuan.me//var/www/html/" local="130711600360000000" remote="130711600360000000" Dst="0" />
<file name="createText.js" server="hekuan.me//var/www/html/" local="130712173180000000" remote="130712173180000000" Dst="0" />
<file name="sylvester.js" server="hekuan.me//var/www/html/" local="130611048620000000" remote="130611048620000000" Dst="0" />
<file name="yepnope.js" server="hekuan.me//var/www/html/" local="130609678840000000" remote="130609678840000000" Dst="0" />
<file name="qiao_OrbitControls.js" server="hekuan.me//var/www/html/" local="130711617440000000" remote="130711617440000000" Dst="0" />
<file name="CanvasRenderer.js" server="hekuan.me//var/www/html/" local="130711536260000000" remote="130711536260000000" Dst="0" />
</dwsync>